README.md
setup.cfg
setup.py
pyPyrTools/Gpyr.py
pyPyrTools/JBhelpers.py
pyPyrTools/LB2idx.py
pyPyrTools/Lpyr.py
pyPyrTools/SCFpyr.py
pyPyrTools/SFpyr.py
pyPyrTools/Spyr.py
pyPyrTools/Wpyr.py
pyPyrTools/__init__.py
pyPyrTools/binomialFilter.py
pyPyrTools/blur.py
pyPyrTools/blurDn.py
pyPyrTools/cconv2.py
pyPyrTools/clip.py
pyPyrTools/comparePyr.py
pyPyrTools/compareRecon.py
pyPyrTools/convolve.c
pyPyrTools/convolve.h
pyPyrTools/corrDn.py
pyPyrTools/edges.c
pyPyrTools/entropy2.py
pyPyrTools/factorial.py
pyPyrTools/histo.py
pyPyrTools/histoMatch.py
pyPyrTools/idx2LB.py
pyPyrTools/imGradient.py
pyPyrTools/imStats.py
pyPyrTools/internal_pointOp.c
pyPyrTools/internal_pointOp.h
pyPyrTools/kurt2.py
pyPyrTools/makeChangelog.py
pyPyrTools/maxPyrHt.py
pyPyrTools/mkAngle.py
pyPyrTools/mkAngularSine.py
pyPyrTools/mkDisc.py
pyPyrTools/mkFract.py
pyPyrTools/mkGaussian.py
pyPyrTools/mkImpulse.py
pyPyrTools/mkR.py
pyPyrTools/mkRamp.py
pyPyrTools/mkSine.py
pyPyrTools/mkSquare.py
pyPyrTools/mkZonePlate.py
pyPyrTools/modulateFlip.py
pyPyrTools/namedFilter.py
pyPyrTools/nextSz.py
pyPyrTools/pointOp.py
pyPyrTools/pyPyrTools.py
pyPyrTools/pyPyrUtils.py
pyPyrTools/pyramid.py
pyPyrTools/range2.py
pyPyrTools/rconv2.py
pyPyrTools/rcosFn.py
pyPyrTools/round.py
pyPyrTools/roundVal.py
pyPyrTools/shift.py
pyPyrTools/showIm.py
pyPyrTools/skew2.py
pyPyrTools/sp0Filters.py
pyPyrTools/sp1Filters.py
pyPyrTools/sp3Filters.py
pyPyrTools/sp5Filters.py
pyPyrTools/steer.py
pyPyrTools/steer2HarmMtx.py
pyPyrTools/strictly_decreasing.py
pyPyrTools/upBlur.py
pyPyrTools/upConv.py
pyPyrTools/var2.py
pyPyrTools/wrap.c
pyPyrTools/zconv2.py
pyPyrTools.egg-info/PKG-INFO
pyPyrTools.egg-info/SOURCES.txt
pyPyrTools.egg-info/dependency_links.txt
pyPyrTools.egg-info/requires.txt
pyPyrTools.egg-info/top_level.txt