Metadata-Version: 1.0
Name: pyPyrTools
Version: 0.2.3
Summary: Python tools for multi-scale image processing, including Laplacian pyramids, Wavelets, and Steerable Pyramids
Home-page: https://github.com/LabForComputationalVision/pyPyrTools
Author: Eero Simoncelli, Rob Young, and William F. Broderick
Author-email: eero.simoncelli@nyu.edu
License: MIT
Keywords: multi-scale image-processing
Platform: UNKNOWN
